zcc_utils/__init__.py
zcc_utils/json_utils.py
zcc_utils/math_utils.py
zcc_utils/time_utils.py
zcc_utils-1.0.12.dist-info/LICENSE
zcc_utils-1.0.12.dist-info/METADATA
zcc_utils-1.0.12.dist-info/WHEEL
zcc_utils-1.0.12.dist-info/top_level.txt
zcc_utils-1.0.12.dist-info/RECORD
