Metadata-Version: 2.1
Name: zcc-utils
Version: 1.0.12
Summary: A uitls package
Home-page: https://gitee.com/week233/zcc_utils
Author: zcc
Author-email: ccz411@outlook.com
License: UNKNOWN
Platform: UNKNOWN
Classifier: Programming Language :: Python :: 3
Classifier: License :: OSI Approved :: MIT License
Classifier: Operating System :: OS Independent
License-File: LICENSE
